md2web/__init__.py
md2web/__main__.py
md2web/__meta__.py
md2web/__version__.py
md2web/blockparser.py
md2web/blockprocessors.py
md2web/cmd.py
md2web/core.py
md2web/htmlparser.py
md2web/inlinepatterns.py
md2web/pep562.py
md2web/postprocessors.py
md2web/preprocessors.py
md2web/serializers.py
md2web/test_tools.py
md2web/treeprocessors.py
md2web/util.py
md2web/extensions/__init__.py
md2web/extensions/abbr.py
md2web/extensions/admonition.py
md2web/extensions/attr_list.py
md2web/extensions/codehilite.py
md2web/extensions/def_list.py
md2web/extensions/extra.py
md2web/extensions/fenced_code.py
md2web/extensions/footnotes.py
md2web/extensions/legacy_attrs.py
md2web/extensions/legacy_em.py
md2web/extensions/md_in_html.py
md2web/extensions/meta.py
md2web/extensions/nl2br.py
md2web/extensions/sane_lists.py
md2web/extensions/smarty.py
md2web/extensions/tables.py
md2web/extensions/toc.py
md2web/extensions/wikilinks.py
md2web-0.0.9.dist-info/LICENSE
md2web-0.0.9.dist-info/METADATA
md2web-0.0.9.dist-info/WHEEL
md2web-0.0.9.dist-info/entry_points.txt
md2web-0.0.9.dist-info/top_level.txt
md2web-0.0.9.dist-info/RECORD
